message_boxes/__init__.py
message_boxes-0.2.2.dist-info/METADATA
message_boxes-0.2.2.dist-info/WHEEL
message_boxes-0.2.2.dist-info/top_level.txt
message_boxes-0.2.2.dist-info/RECORD
